blume/__init__.py
blume/blitting.py
blume/cod.py
blume/console.py
blume/cpr.py
blume/dataklasses.py
blume/docs.py
blume/dss.py
blume/eggshow.py
blume/farm.py
blume/fitscan.py
blume/gaia.py
blume/gw.py
blume/hp.py
blume/legend.py
blume/magic.py
blume/magic2.py
blume/mb.py
blume/mclock2.py
blume/metagit.py
blume/modnar.py
blume/mosaic.py
blume/noligo.py
blume/rcparms.py
blume/table.py
blume/talk.py
blume/taybell.py
blume/teakhat.py
blume/train.py
blume/twins.py
blume/balls/__init__.py
blume/balls/sudoku.py
blume/examples/__init__.py
blume/examples/chess_table.py
blume/examples/cod.py
blume/examples/cpr.py
blume/examples/get.py
blume/examples/iyield.py
blume/examples/legendary.py
blume/examples/ligoview.py
blume/examples/multiline.py
blume/examples/shortify.py
blume/examples/show.py
blume/examples/table_demo.py
blume-0.2.7.dist-info/LICENSE
blume-0.2.7.dist-info/METADATA
blume-0.2.7.dist-info/WHEEL
blume-0.2.7.dist-info/dependency_links.txt
blume-0.2.7.dist-info/top_level.txt
blume-0.2.7.dist-info/RECORD
