Metadata-Version: 2.1
Name: blume
Version: 0.2.7
Summary: Better looking tables for matplotlib
Home-page: https://github.com/swfiua/blume
Author: The Matplotlib Team, John Hunter, Johnny Gill
Author-email: swfiua@gmail.com
License: Matplotlib
Keywords: matplotlib table
Classifier: Development Status :: 4 - Beta
Classifier: Intended Audience :: Science/Research
Classifier: Programming Language :: Python :: 3.6
License-File: LICENSE
Requires-Dist: matplotlib >=3.1
